neuromeka_isaacsim/__init__.py
neuromeka_isaacsim/neuromeka_isaacsim_install.py
neuromeka_isaacsim/omni.isaacsim_bridge.extension.zip
neuromeka_isaacsim/neuromeka-isaacsim/conty_bridge.usd
neuromeka_isaacsim/neuromeka-isaacsim/Robots/indy7.usd
neuromeka_isaacsim-0.0.5.dist-info/METADATA
neuromeka_isaacsim-0.0.5.dist-info/WHEEL
neuromeka_isaacsim-0.0.5.dist-info/entry_points.txt
neuromeka_isaacsim-0.0.5.dist-info/top_level.txt
neuromeka_isaacsim-0.0.5.dist-info/RECORD
