Metadata-Version: 2.1
Name: neuromeka-isaacsim
Version: 0.0.5
Summary: Isaac Sim extension for Neuromeka robots
Author-email: Neuromeka <technical-support@neuromeka.com>
License: MIT
Requires-Python: <3.11,>=3.10
Provides-Extra: dev
Requires-Dist: pytest; extra == "dev"
Requires-Dist: black; extra == "dev"
